gee_python_tools/__init__.py
gee_python_tools/cloudmask.py
gee_python_tools/landsat_composite.py
py_gee_tools-0.1.dist-info/LICENSE
py_gee_tools-0.1.dist-info/METADATA
py_gee_tools-0.1.dist-info/WHEEL
py_gee_tools-0.1.dist-info/top_level.txt
py_gee_tools-0.1.dist-info/RECORD
