Metadata-Version: 2.1
Name: py-gee-tools
Version: 0.1
Summary: Helper package to work with the Google Earth Engine Python Library
Home-page: https://github.com/elbeejay/py_gee_tools
Author: Jayaram Hariharan
Author-email: jayaram.hariharan@utexas.edu
License: UNKNOWN
Keywords: remote sensing, landsat, satellite, Google, Earth Engine, Google Earth Engine, modis,sentinel,sentinel-2
Platform: UNKNOWN
Classifier: Development Status :: 3 - Alpha
Classifier: Programming Language :: Python :: 3.6
Classifier: Programming Language :: Python :: 3.7
Classifier: Programming Language :: Python :: 3.8
Classifier: License :: OSI Approved :: Apache Software License
Requires-Python: >=3.6
Requires-Dist: earthengine-api
